ghc_utils/__init__.py
ghc_utils/cli.py
ghc_utils/ghc_utils.py
ghc_utils-0.1.2.dist-info/LICENSE
ghc_utils-0.1.2.dist-info/METADATA
ghc_utils-0.1.2.dist-info/WHEEL
ghc_utils-0.1.2.dist-info/entry_points.txt
ghc_utils-0.1.2.dist-info/top_level.txt
ghc_utils-0.1.2.dist-info/RECORD
