Metadata-Version: 2.1
Name: ghc-utils
Version: 0.1.2
Summary: utilies for github classroom
Home-page: https://github.com/aronwc/ghc-utils
Author: Aron C
Author-email: aronwc@gmail.com
License: GNU General Public License v3
Keywords: ghc_utils
Platform: UNKNOWN
Classifier: Development Status :: 2 - Pre-Alpha
Classifier: Intended Audience :: Developers
Classifier: License :: OSI Approved :: GNU General Public License v3 (GPLv3)
Classifier: Natural Language :: English
Classifier: Programming Language :: Python :: 3
Classifier: Programming Language :: Python :: 3.5
Classifier: Programming Language :: Python :: 3.6
Classifier: Programming Language :: Python :: 3.7
Classifier: Programming Language :: Python :: 3.8
Requires-Python: >=3.5
Requires-Dist: Click (==7.0)
Requires-Dist: github3.py
